zhinst/deviceutils/__init__.py
zhinst/deviceutils/shfqa.py
zhinst/deviceutils/shfqc.py
zhinst/deviceutils/shfsg.py
zhinst/utils/__init__.py
zhinst/utils/_version.py
zhinst/utils/api_compatibility.py
zhinst/utils/auto_generate_functions.py
zhinst/utils/device_status.py
zhinst/utils/exceptions.py
zhinst/utils/feedback_model.py
zhinst/utils/shf_sweeper.py
zhinst/utils/shfsg.py
zhinst/utils/utils.py
zhinst/utils/shfqa/__init__.py
zhinst/utils/shfqa/multistate.py
zhinst/utils/shfqa/shfqa.py
zhinst/utils/shfqc/__init__.py
zhinst/utils/shfqc/shfqc.py
zhinst_utils-0.7.1.dist-info/LICENSE
zhinst_utils-0.7.1.dist-info/METADATA
zhinst_utils-0.7.1.dist-info/WHEEL
zhinst_utils-0.7.1.dist-info/top_level.txt
zhinst_utils-0.7.1.dist-info/RECORD
