Metadata-Version: 2.1
Name: zhinst-utils
Version: 0.7.1
Summary: Zurich Instruments utils for device control
Home-page: https://github.com/zhinst/zhinst-utils
Author: Zurich Instrument
Author-email: info@zhinst.com
Project-URL: Bug Tracker, https://github.com/zhinst/zhinst-utils/issues
Classifier: Programming Language :: Python :: 3
Classifier: License :: OSI Approved :: MIT License
Classifier: Operating System :: OS Independent
Requires-Python: >=3.7
License-File: LICENSE
Requires-Dist: numpy >=1.14
Requires-Dist: zhinst-core >=23.06
Requires-Dist: zhinst-timing-models
